fast_dataset_cleaner/__init__.py
fast_dataset_cleaner/command.py
fast_dataset_cleaner/parser.py
fast_dataset_cleaner/run.py
fast_dataset_cleaner/back/__init__.py
fast_dataset_cleaner/back/constants.py
fast_dataset_cleaner/back/image_builder.py
fast_dataset_cleaner/back/main.py
fast_dataset_cleaner/back/api/__init__.py
fast_dataset_cleaner/back/api/routes.py
fast_dataset_cleaner/back/api/utils.py
fast_dataset_cleaner/back/services/AnnotationService.py
fast_dataset_cleaner/back/services/ImageService.py
fast_dataset_cleaner/back/services/__init__.py
fast_dataset_cleaner/front/build/asset-manifest.json
fast_dataset_cleaner/front/build/favicon.ico
fast_dataset_cleaner/front/build/index.html
fast_dataset_cleaner/front/build/logo192.png
fast_dataset_cleaner/front/build/logo512.png
fast_dataset_cleaner/front/build/manifest.json
fast_dataset_cleaner/front/build/precache-manifest.6773f17ca5758fc63d6a1a6973385418.js
fast_dataset_cleaner/front/build/precache-manifest.cfab3d99be42a3083cd1a27ca238038e.js
fast_dataset_cleaner/front/build/robots.txt
fast_dataset_cleaner/front/build/service-worker.js
fast_dataset_cleaner/front/build/static/css/main.e59da69f.chunk.css
fast_dataset_cleaner/front/build/static/css/main.e59da69f.chunk.css.map
fast_dataset_cleaner/front/build/static/js/2.3a10aaba.chunk.js
fast_dataset_cleaner/front/build/static/js/2.3a10aaba.chunk.js.LICENSE.txt
fast_dataset_cleaner/front/build/static/js/2.3a10aaba.chunk.js.map
fast_dataset_cleaner/front/build/static/js/2.8f7f9217.chunk.js
fast_dataset_cleaner/front/build/static/js/2.8f7f9217.chunk.js.LICENSE.txt
fast_dataset_cleaner/front/build/static/js/2.8f7f9217.chunk.js.map
fast_dataset_cleaner/front/build/static/js/main.842bbfb2.chunk.js
fast_dataset_cleaner/front/build/static/js/main.842bbfb2.chunk.js.map
fast_dataset_cleaner/front/build/static/js/main.b85ab40e.chunk.js
fast_dataset_cleaner/front/build/static/js/main.b85ab40e.chunk.js.map
fast_dataset_cleaner/front/build/static/js/runtime-main.2fa1d660.js
fast_dataset_cleaner-1.0.0.dist-info/LICENSE
fast_dataset_cleaner-1.0.0.dist-info/METADATA
fast_dataset_cleaner-1.0.0.dist-info/WHEEL
fast_dataset_cleaner-1.0.0.dist-info/top_level.txt
fast_dataset_cleaner-1.0.0.dist-info/RECORD
