Metadata-Version: 2.1
Name: fast-dataset-cleaner
Version: 1.0.0
Summary: Web platform for fast image dataset cleaning
Home-page: https://github.com/PhotoRoom/fast-dataset-cleaner
Author: Thomas Chabal
Author-email: t.chabal@hotmail.fr
License: UNKNOWN
Keywords: annotation,dataset cleaning,binary annotation,fast dataset cleaner,image dataset
Platform: UNKNOWN
Classifier: Programming Language :: Python :: 3
Classifier: License :: OSI Approved :: MIT License
Classifier: Operating System :: OS Independent
Requires-Python: >=3.6
Requires-Dist: Flask (==1.1.2)
Requires-Dist: Flask-Cors (==3.0.8)
Requires-Dist: flask-restx (==0.2.0)
Requires-Dist: numpy
Requires-Dist: opencv-python
Requires-Dist: pandas
Requires-Dist: Pillow
Requires-Dist: Werkzeug (==0.16.1)
